llamacpypy/__init__.py
llamacpypy/_core.cpython-39-darwin.so
llamacpypy/llama.py
llamacpypy-0.1.0.dist-info/METADATA
llamacpypy-0.1.0.dist-info/WHEEL
llamacpypy-0.1.0.dist-info/entry_points.txt
llamacpypy-0.1.0.dist-info/RECORD
