Metadata-Version: 2.1
Name: llamacpypy
Version: 0.1.0
Summary: Python bindings for llama.cpp
Author-Email: Emanuel Seemann <github@emanuelseemann.ch>
License: MIT License
Classifier: License :: OSI Approved :: MIT License
Classifier: Programming Language :: Python
Classifier: Programming Language :: Python :: 3
Classifier: Programming Language :: C++
Project-URL: Homepage, https://github.com/seemanne/llamacpypy
Requires-Dist: pybind11>=2.10.4
